pandaz/1_descriptive_stats.py
pandaz/2_data_imputation.py
pandaz/3_data_visualisation.py
pandaz/4_supervised_learning.py
pandaz/5_unsupervised_learning.py
pandaz/6_timeseriesforecasting.py
pandaz/7_outlier_detection.py
pandaz/8_SMOTE.py
pandaz/9_inferential_stats.py
pandaz/__init__.py
pandaz-3.4.2.dist-info/LICENSE
pandaz-3.4.2.dist-info/METADATA
pandaz-3.4.2.dist-info/WHEEL
pandaz-3.4.2.dist-info/top_level.txt
pandaz-3.4.2.dist-info/RECORD
