Metadata-Version: 2.1
Name: pandaz
Version: 3.4.2
Summary: A package that facilitates efficient coding and development
Author: Tom Hanks
Author-email: <tomhanks02@gmail.com>
Keywords: python,development,productivity,utilities
Classifier: Development Status :: 5 - Production/Stable
Classifier: Intended Audience :: Developers
Classifier: Programming Language :: Python :: 3
Classifier: Operating System :: OS Independent
Classifier: License :: OSI Approved :: MIT License
Classifier: Topic :: Software Development :: Libraries :: Python Modules
License-File: LICENSE
